{"status":"success","data":{"lagos":{"executive":{"governor":"Sheriff Oborevwori","deputyGovernor":"Obafemi Hamzat"},"legislature":{"speaker":"Mudashiru Obasa"}},"abuja":{"executive":{"governor":"Nyesom Wike","deputyGovernor":"Mohammed Hassan"},"legislature":{"speaker":"Tajudeen Abbas"}},"delta":{"executive":{"governor":"Sheriff Oborevwori","deputyGovernor":"Olorogun Kingsley Otuaro"},"legislature":{"speaker":"Oborevwori Sheriff"}},"akwaibom":{"executive":{"governor":"Umo Eno","deputyGovernor":"Emmanuel Akpan"},"legislature":{"speaker":"Udo Kieran"}},"rivers":{"executive":{"governor":"Siminalayi Fubara","deputyGovernor":"Ipalibo Harry Banigo"},"legislature":{"speaker":"Ikuinyi-Owaji Ibani"}},"crossriver":{"executive":{"governor":"Benedict Ayade","deputyGovernor":"Ivara Esu"},"legislature":{"speaker":"Elijah Akpan"}},"abia":{"executive":{"governor":"Alex Otti","deputyGovernor":"Ifeanyi Ubah"},"legislature":{"speaker":"Chinedum Orji"}},"adamawa":{"executive":{"governor":"Ahmadu Fintiri","deputyGovernor":"Kalap Malat"},"legislature":{"speaker":"Abbas Gaji"}},"bauchi":{"executive":{"governor":"Bala Mohammed","deputyGovernor":"Babayo Mohammed"},"legislature":{"speaker":"Abdulkadir Abubakar"}},"benin":{"executive":{"governor":"Godwin Obaseki","deputyGovernor":"Philip Shaibu"},"legislature":{"speaker":"Marcus Onobun"}},"kebbi":{"executive":{"governor":"Nasir Idris","deputyGovernor":"Samaila Yombe"},"legislature":{"speaker":"Abubakar Lolo"}},"kaduna":{"executive":{"governor":"Uba Sani","deputyGovernor":"Hadiza Balarabe"},"legislature":{"speaker":"Isaac Auta"}}}}